{
  "generatedAt": "2026-06-19T20:57:13.557747+00:00",
  "mode": "paper",
  "halted": false,
  "haltReason": null,
  "account": {
    "equity": 99997.845,
    "cash": 58589.78,
    "buyingPower": 58589.78,
    "peakEquity": 100064.26,
    "currentDrawdownPct": 0.0006637234912845006,
    "dailyStartEquity": 100000.0,
    "dayPnl": -2.155,
    "dayPnlPct": -2.155e-05
  },
  "equityCurve": [
    {
      "t": "2026-06-04T23:39:01.443559+00:00",
      "equity": 100000.0,
      "drawdownPct": 0.0
    },
    {
      "t": "2026-06-05T02:57:13.417021+00:00",
      "equity": 100000.0,
      "drawdownPct": 0.0
    },
    {
      "t": "2026-06-05T17:01:59.596037+00:00",
      "equity": 100000.0,
      "drawdownPct": 0.0
    },
    {
      "t": "2026-06-05T21:12:11.564709+00:00",
      "equity": 99900.285,
      "drawdownPct": 0.0009971499999999651
    },
    {
      "t": "2026-06-08T20:37:43.456981+00:00",
      "equity": 99953.81,
      "drawdownPct": 0.00046190000000002326
    },
    {
      "t": "2026-06-08T21:28:46.768866+00:00",
      "equity": 99953.81,
      "drawdownPct": 0.00046190000000002326
    },
    {
      "t": "2026-06-09T21:25:25.391734+00:00",
      "equity": 99811.025,
      "drawdownPct": 0.0018897500000000583
    },
    {
      "t": "2026-06-10T21:47:01.115866+00:00",
      "equity": 99573.075,
      "drawdownPct": 0.004269250000000029
    },
    {
      "t": "2026-06-11T21:51:25.628301+00:00",
      "equity": 99787.94,
      "drawdownPct": 0.002120599999999977
    },
    {
      "t": "2026-06-12T21:20:48.053819+00:00",
      "equity": 99800.305,
      "drawdownPct": 0.0019969500000000698
    },
    {
      "t": "2026-06-15T22:06:34.054886+00:00",
      "equity": 99945.77,
      "drawdownPct": 0.0005422999999999592
    },
    {
      "t": "2026-06-16T22:03:21.253615+00:00",
      "equity": 99948.145,
      "drawdownPct": 0.0005185499999999592
    },
    {
      "t": "2026-06-17T21:46:36.785509+00:00",
      "equity": 99950.055,
      "drawdownPct": 0.0004994500000000698
    },
    {
      "t": "2026-06-18T21:51:57.918061+00:00",
      "equity": 99997.845,
      "drawdownPct": 2.1549999999988357e-05
    },
    {
      "t": "2026-06-19T20:57:07.837140+00:00",
      "equity": 99997.845,
      "drawdownPct": 2.1549999999988357e-05
    }
  ],
  "positions": [
    {
      "ticker": "DBA",
      "assetClass": "etf",
      "quantity": 306.0,
      "avgPrice": 26.42,
      "lastPrice": 26.63,
      "marketValue": 8148.78,
      "unrealizedPnl": 64.26,
      "unrealizedPnlPct": 0.007948523845571537,
      "weightPct": 0.08148955609993395,
      "strategyId": "multi_asset_trend"
    },
    {
      "ticker": "DBC",
      "assetClass": "etf",
      "quantity": 132.0,
      "avgPrice": 29.27,
      "lastPrice": 27.635,
      "marketValue": 3647.82,
      "unrealizedPnl": -215.82,
      "unrealizedPnlPct": -0.05585924154424325,
      "weightPct": 0.03647898612215093,
      "strategyId": "multi_asset_trend"
    },
    {
      "ticker": "EFA",
      "assetClass": "etf",
      "quantity": 42.0,
      "avgPrice": 102.96,
      "lastPrice": 104.39,
      "marketValue": 4384.38,
      "unrealizedPnl": 60.06,
      "unrealizedPnlPct": 0.013888888888888888,
      "weightPct": 0.04384474485425161,
      "strategyId": "multi_asset_trend"
    },
    {
      "ticker": "GLD",
      "assetClass": "etf",
      "quantity": 8.0,
      "avgPrice": 398.5,
      "lastPrice": 387.08,
      "marketValue": 3096.64,
      "unrealizedPnl": -91.36,
      "unrealizedPnlPct": -0.028657465495608533,
      "weightPct": 0.030967067340301184,
      "strategyId": "multi_asset_trend"
    },
    {
      "ticker": "SPY",
      "assetClass": "etf",
      "quantity": 8.0,
      "avgPrice": 743.79,
      "lastPrice": 746.75,
      "marketValue": 5974.0,
      "unrealizedPnl": 23.68,
      "unrealizedPnlPct": 0.003979617902902701,
      "weightPct": 0.059741287424744,
      "strategyId": "multi_asset_trend"
    },
    {
      "ticker": "UUP",
      "assetClass": "etf",
      "quantity": 571.0,
      "avgPrice": 28.02,
      "lastPrice": 28.295,
      "marketValue": 16156.445,
      "unrealizedPnl": 157.025,
      "unrealizedPnlPct": 0.009814418272662384,
      "weightPct": 0.16156793178893006,
      "strategyId": "multi_asset_trend"
    }
  ],
  "trades": [],
  "strategies": [
    {
      "id": "multi_asset_trend",
      "name": "Multi-Asset Trend (inverse-vol)",
      "status": "paper",
      "allocationPct": 1.0,
      "driftStatus": "warn"
    }
  ],
  "paperGate": {
    "startDate": "2026-06-04T23:39:01.443559+00:00",
    "daysElapsed": 15,
    "daysRequired": 30,
    "rollingSharpe": -0.014340181422078298,
    "targetSharpe": 1.0,
    "withinBacktestBand": false
  },
  "gauntlet": [],
  "alerts": [
    {
      "t": "2026-06-19T20:57:13.557747+00:00",
      "level": "info",
      "kind": "drift",
      "message": "collecting live data (14/30)"
    }
  ],
  "books": [
    {
      "id": "deployed",
      "name": "Multi-Asset Trend (inverse-vol)",
      "kind": "deployed",
      "status": "paper",
      "halted": false,
      "account": {
        "equity": 99997.845,
        "cash": 58589.78,
        "buyingPower": 58589.78,
        "peakEquity": 100064.26,
        "currentDrawdownPct": 0.0006637234912845006,
        "dailyStartEquity": 100000.0,
        "dayPnl": -2.155,
        "dayPnlPct": -2.155e-05
      },
      "equityCurve": [
        {
          "t": "2026-06-04T23:39:01.443559+00:00",
          "equity": 100000.0,
          "drawdownPct": 0.0
        },
        {
          "t": "2026-06-05T02:57:13.417021+00:00",
          "equity": 100000.0,
          "drawdownPct": 0.0
        },
        {
          "t": "2026-06-05T17:01:59.596037+00:00",
          "equity": 100000.0,
          "drawdownPct": 0.0
        },
        {
          "t": "2026-06-05T21:12:11.564709+00:00",
          "equity": 99900.285,
          "drawdownPct": 0.0009971499999999651
        },
        {
          "t": "2026-06-08T20:37:43.456981+00:00",
          "equity": 99953.81,
          "drawdownPct": 0.00046190000000002326
        },
        {
          "t": "2026-06-08T21:28:46.768866+00:00",
          "equity": 99953.81,
          "drawdownPct": 0.00046190000000002326
        },
        {
          "t": "2026-06-09T21:25:25.391734+00:00",
          "equity": 99811.025,
          "drawdownPct": 0.0018897500000000583
        },
        {
          "t": "2026-06-10T21:47:01.115866+00:00",
          "equity": 99573.075,
          "drawdownPct": 0.004269250000000029
        },
        {
          "t": "2026-06-11T21:51:25.628301+00:00",
          "equity": 99787.94,
          "drawdownPct": 0.002120599999999977
        },
        {
          "t": "2026-06-12T21:20:48.053819+00:00",
          "equity": 99800.305,
          "drawdownPct": 0.0019969500000000698
        },
        {
          "t": "2026-06-15T22:06:34.054886+00:00",
          "equity": 99945.77,
          "drawdownPct": 0.0005422999999999592
        },
        {
          "t": "2026-06-16T22:03:21.253615+00:00",
          "equity": 99948.145,
          "drawdownPct": 0.0005185499999999592
        },
        {
          "t": "2026-06-17T21:46:36.785509+00:00",
          "equity": 99950.055,
          "drawdownPct": 0.0004994500000000698
        },
        {
          "t": "2026-06-18T21:51:57.918061+00:00",
          "equity": 99997.845,
          "drawdownPct": 2.1549999999988357e-05
        },
        {
          "t": "2026-06-19T20:57:07.837140+00:00",
          "equity": 99997.845,
          "drawdownPct": 2.1549999999988357e-05
        }
      ],
      "positions": [
        {
          "ticker": "DBA",
          "assetClass": "etf",
          "quantity": 306.0,
          "avgPrice": 26.42,
          "lastPrice": 26.63,
          "marketValue": 8148.78,
          "unrealizedPnl": 64.26,
          "unrealizedPnlPct": 0.007948523845571537,
          "weightPct": 0.08148955609993395,
          "strategyId": "multi_asset_trend"
        },
        {
          "ticker": "DBC",
          "assetClass": "etf",
          "quantity": 132.0,
          "avgPrice": 29.27,
          "lastPrice": 27.635,
          "marketValue": 3647.82,
          "unrealizedPnl": -215.82,
          "unrealizedPnlPct": -0.05585924154424325,
          "weightPct": 0.03647898612215093,
          "strategyId": "multi_asset_trend"
        },
        {
          "ticker": "EFA",
          "assetClass": "etf",
          "quantity": 42.0,
          "avgPrice": 102.96,
          "lastPrice": 104.39,
          "marketValue": 4384.38,
          "unrealizedPnl": 60.06,
          "unrealizedPnlPct": 0.013888888888888888,
          "weightPct": 0.04384474485425161,
          "strategyId": "multi_asset_trend"
        },
        {
          "ticker": "GLD",
          "assetClass": "etf",
          "quantity": 8.0,
          "avgPrice": 398.5,
          "lastPrice": 387.08,
          "marketValue": 3096.64,
          "unrealizedPnl": -91.36,
          "unrealizedPnlPct": -0.028657465495608533,
          "weightPct": 0.030967067340301184,
          "strategyId": "multi_asset_trend"
        },
        {
          "ticker": "SPY",
          "assetClass": "etf",
          "quantity": 8.0,
          "avgPrice": 743.79,
          "lastPrice": 746.75,
          "marketValue": 5974.0,
          "unrealizedPnl": 23.68,
          "unrealizedPnlPct": 0.003979617902902701,
          "weightPct": 0.059741287424744,
          "strategyId": "multi_asset_trend"
        },
        {
          "ticker": "UUP",
          "assetClass": "etf",
          "quantity": 571.0,
          "avgPrice": 28.02,
          "lastPrice": 28.295,
          "marketValue": 16156.445,
          "unrealizedPnl": 157.025,
          "unrealizedPnlPct": 0.009814418272662384,
          "weightPct": 0.16156793178893006,
          "strategyId": "multi_asset_trend"
        }
      ],
      "paperGate": {
        "startDate": "2026-06-04T23:39:01.443559+00:00",
        "daysElapsed": 15,
        "daysRequired": 30,
        "rollingSharpe": -0.014340181422078298,
        "targetSharpe": 1.0,
        "withinBacktestBand": false
      },
      "summary": {
        "totalReturnPct": -2.1550000000036817e-05,
        "sharpe": -0.014340181422078298,
        "maxDrawdownPct": 0.004269250000000029,
        "dayPnlPct": -2.155e-05,
        "sessions": 15
      }
    },
    {
      "id": "cross_sec_momo",
      "name": "Cross-Sectional Momentum",
      "kind": "experiment",
      "status": "paper",
      "halted": false,
      "account": {
        "equity": 99658.339905,
        "cash": 63383.324905,
        "buyingPower": 63383.324905,
        "peakEquity": 100000.0,
        "currentDrawdownPct": 0.00341660095,
        "dailyStartEquity": 100000.0,
        "dayPnl": -341.660095,
        "dayPnlPct": -0.00341660095
      },
      "equityCurve": [
        {
          "t": "2026-06-08T20:37:46.330142+00:00",
          "equity": 100000.0,
          "drawdownPct": 0.0
        },
        {
          "t": "2026-06-08T21:28:49.463696+00:00",
          "equity": 99963.419905,
          "drawdownPct": 0.0003658009499999753
        },
        {
          "t": "2026-06-09T21:25:28.211990+00:00",
          "equity": 99787.104905,
          "drawdownPct": 0.0021289509499999985
        },
        {
          "t": "2026-06-10T21:47:06.359195+00:00",
          "equity": 99431.619905,
          "drawdownPct": 0.005683800950000004
        },
        {
          "t": "2026-06-11T21:51:29.612356+00:00",
          "equity": 99914.074905,
          "drawdownPct": 0.0008592509499999869
        },
        {
          "t": "2026-06-12T21:20:53.524946+00:00",
          "equity": 99932.689905,
          "drawdownPct": 0.0006731009499999346
        },
        {
          "t": "2026-06-15T22:06:39.340799+00:00",
          "equity": 99999.909905,
          "drawdownPct": 9.009500000684057e-07
        },
        {
          "t": "2026-06-16T22:03:28.516162+00:00",
          "equity": 99822.279905,
          "drawdownPct": 0.0017772009499999694
        },
        {
          "t": "2026-06-17T21:46:43.021831+00:00",
          "equity": 99498.314905,
          "drawdownPct": 0.005016850949999934
        },
        {
          "t": "2026-06-18T21:52:03.430422+00:00",
          "equity": 99658.339905,
          "drawdownPct": 0.003416600949999993
        },
        {
          "t": "2026-06-19T20:57:12.910878+00:00",
          "equity": 99658.339905,
          "drawdownPct": 0.003416600949999993
        }
      ],
      "positions": [
        {
          "ticker": "DBC",
          "assetClass": "etf",
          "quantity": 341.0,
          "avgPrice": 29.48946,
          "lastPrice": 27.635,
          "marketValue": 9423.535,
          "unrealizedPnl": -632.37086,
          "unrealizedPnlPct": -0.06288551909733173,
          "weightPct": 0.0945584183820747,
          "strategyId": "multi_asset_trend"
        },
        {
          "ticker": "EFA",
          "assetClass": "etf",
          "quantity": 107.0,
          "avgPrice": 103.0029,
          "lastPrice": 104.39,
          "marketValue": 11169.73,
          "unrealizedPnl": 148.4197,
          "unrealizedPnlPct": 0.013466611134249618,
          "weightPct": 0.11208023343202006,
          "strategyId": "multi_asset_trend"
        },
        {
          "ticker": "SPY",
          "assetClass": "etf",
          "quantity": 21.0,
          "avgPrice": 739.974235,
          "lastPrice": 746.75,
          "marketValue": 15681.75,
          "unrealizedPnl": 142.291065,
          "unrealizedPnlPct": 0.009156758005229736,
          "weightPct": 0.15735511965128796,
          "strategyId": "multi_asset_trend"
        }
      ],
      "paperGate": {
        "startDate": "2026-06-08T20:37:46.330142+00:00",
        "daysElapsed": 11,
        "daysRequired": 30,
        "rollingSharpe": -2.2957513181745193,
        "targetSharpe": 1.0,
        "withinBacktestBand": false
      },
      "summary": {
        "totalReturnPct": -0.0034166009499999594,
        "sharpe": -2.2957513181745193,
        "maxDrawdownPct": 0.005683800950000004,
        "dayPnlPct": -0.00341660095,
        "sessions": 11
      }
    },
    {
      "id": "dual_momentum",
      "name": "Dual Momentum (GEM)",
      "kind": "experiment",
      "status": "paper",
      "halted": false,
      "account": {
        "equity": 100000.0,
        "cash": 100000.0,
        "buyingPower": 100000.0,
        "peakEquity": 100000.0,
        "currentDrawdownPct": 0.0,
        "dailyStartEquity": 100000.0,
        "dayPnl": 0.0,
        "dayPnlPct": 0.0
      },
      "equityCurve": [
        {
          "t": "2026-06-08T20:37:45.716237+00:00",
          "equity": 100000.0,
          "drawdownPct": 0.0
        },
        {
          "t": "2026-06-08T21:28:48.904894+00:00",
          "equity": 100000.0,
          "drawdownPct": 0.0
        },
        {
          "t": "2026-06-09T21:25:27.643360+00:00",
          "equity": 100000.0,
          "drawdownPct": 0.0
        },
        {
          "t": "2026-06-10T21:47:04.487452+00:00",
          "equity": 100000.0,
          "drawdownPct": 0.0
        },
        {
          "t": "2026-06-11T21:51:28.079647+00:00",
          "equity": 100000.0,
          "drawdownPct": 0.0
        },
        {
          "t": "2026-06-12T21:20:52.646660+00:00",
          "equity": 100000.0,
          "drawdownPct": 0.0
        },
        {
          "t": "2026-06-15T22:06:38.727686+00:00",
          "equity": 100000.0,
          "drawdownPct": 0.0
        },
        {
          "t": "2026-06-16T22:03:26.709954+00:00",
          "equity": 100000.0,
          "drawdownPct": 0.0
        },
        {
          "t": "2026-06-17T21:46:41.728118+00:00",
          "equity": 100000.0,
          "drawdownPct": 0.0
        },
        {
          "t": "2026-06-18T21:52:02.535215+00:00",
          "equity": 100000.0,
          "drawdownPct": 0.0
        },
        {
          "t": "2026-06-19T20:57:12.203416+00:00",
          "equity": 100000.0,
          "drawdownPct": 0.0
        }
      ],
      "positions": [],
      "paperGate": {
        "startDate": "2026-06-08T20:37:45.716237+00:00",
        "daysElapsed": 11,
        "daysRequired": 30,
        "rollingSharpe": 0.0,
        "targetSharpe": 1.0,
        "withinBacktestBand": false
      },
      "summary": {
        "totalReturnPct": 0.0,
        "sharpe": 0.0,
        "maxDrawdownPct": 0.0,
        "dayPnlPct": 0.0,
        "sessions": 11
      }
    },
    {
      "id": "etf_rotation",
      "name": "Sector ETF Rotation",
      "kind": "experiment",
      "status": "paper",
      "halted": false,
      "account": {
        "equity": 100000.0,
        "cash": 100000.0,
        "buyingPower": 100000.0,
        "peakEquity": 100000.0,
        "currentDrawdownPct": 0.0,
        "dailyStartEquity": 100000.0,
        "dayPnl": 0.0,
        "dayPnlPct": 0.0
      },
      "equityCurve": [
        {
          "t": "2026-06-08T20:37:45.934700+00:00",
          "equity": 100000.0,
          "drawdownPct": 0.0
        },
        {
          "t": "2026-06-08T21:28:49.092969+00:00",
          "equity": 100000.0,
          "drawdownPct": 0.0
        },
        {
          "t": "2026-06-09T21:25:27.849400+00:00",
          "equity": 100000.0,
          "drawdownPct": 0.0
        },
        {
          "t": "2026-06-10T21:47:05.317704+00:00",
          "equity": 100000.0,
          "drawdownPct": 0.0
        },
        {
          "t": "2026-06-11T21:51:28.830646+00:00",
          "equity": 100000.0,
          "drawdownPct": 0.0
        },
        {
          "t": "2026-06-12T21:20:52.997695+00:00",
          "equity": 100000.0,
          "drawdownPct": 0.0
        },
        {
          "t": "2026-06-15T22:06:38.947104+00:00",
          "equity": 100000.0,
          "drawdownPct": 0.0
        },
        {
          "t": "2026-06-16T22:03:27.586881+00:00",
          "equity": 100000.0,
          "drawdownPct": 0.0
        },
        {
          "t": "2026-06-17T21:46:42.257083+00:00",
          "equity": 100000.0,
          "drawdownPct": 0.0
        },
        {
          "t": "2026-06-18T21:52:02.880944+00:00",
          "equity": 100000.0,
          "drawdownPct": 0.0
        },
        {
          "t": "2026-06-19T20:57:12.426902+00:00",
          "equity": 100000.0,
          "drawdownPct": 0.0
        }
      ],
      "positions": [],
      "paperGate": {
        "startDate": "2026-06-08T20:37:45.934700+00:00",
        "daysElapsed": 11,
        "daysRequired": 30,
        "rollingSharpe": 0.0,
        "targetSharpe": 1.0,
        "withinBacktestBand": false
      },
      "summary": {
        "totalReturnPct": 0.0,
        "sharpe": 0.0,
        "maxDrawdownPct": 0.0,
        "dayPnlPct": 0.0,
        "sessions": 11
      }
    },
    {
      "id": "rsi2_spy",
      "name": "RSI(2) Mean Reversion (SPY)",
      "kind": "experiment",
      "status": "paper",
      "halted": false,
      "account": {
        "equity": 100000.0,
        "cash": 100000.0,
        "buyingPower": 100000.0,
        "peakEquity": 100000.0,
        "currentDrawdownPct": 0.0,
        "dailyStartEquity": 100000.0,
        "dayPnl": 0.0,
        "dayPnlPct": 0.0
      },
      "equityCurve": [
        {
          "t": "2026-06-08T20:37:46.224733+00:00",
          "equity": 100000.0,
          "drawdownPct": 0.0
        },
        {
          "t": "2026-06-08T21:28:49.368606+00:00",
          "equity": 100000.0,
          "drawdownPct": 0.0
        },
        {
          "t": "2026-06-09T21:25:28.110769+00:00",
          "equity": 100000.0,
          "drawdownPct": 0.0
        },
        {
          "t": "2026-06-10T21:47:06.014510+00:00",
          "equity": 100000.0,
          "drawdownPct": 0.0
        },
        {
          "t": "2026-06-11T21:51:29.329818+00:00",
          "equity": 100000.0,
          "drawdownPct": 0.0
        },
        {
          "t": "2026-06-12T21:20:53.363834+00:00",
          "equity": 100000.0,
          "drawdownPct": 0.0
        },
        {
          "t": "2026-06-15T22:06:39.239031+00:00",
          "equity": 100000.0,
          "drawdownPct": 0.0
        },
        {
          "t": "2026-06-16T22:03:28.205083+00:00",
          "equity": 100000.0,
          "drawdownPct": 0.0
        },
        {
          "t": "2026-06-17T21:46:42.655063+00:00",
          "equity": 100000.0,
          "drawdownPct": 0.0
        },
        {
          "t": "2026-06-18T21:52:03.267755+00:00",
          "equity": 100000.0,
          "drawdownPct": 0.0
        },
        {
          "t": "2026-06-19T20:57:12.694625+00:00",
          "equity": 100000.0,
          "drawdownPct": 0.0
        }
      ],
      "positions": [],
      "paperGate": {
        "startDate": "2026-06-08T20:37:46.224733+00:00",
        "daysElapsed": 11,
        "daysRequired": 30,
        "rollingSharpe": 0.0,
        "targetSharpe": 1.0,
        "withinBacktestBand": false
      },
      "summary": {
        "totalReturnPct": 0.0,
        "sharpe": 0.0,
        "maxDrawdownPct": 0.0,
        "dayPnlPct": 0.0,
        "sessions": 11
      }
    },
    {
      "id": "trend_bond",
      "name": "Trend + Bond Rotation",
      "kind": "experiment",
      "status": "paper",
      "halted": false,
      "account": {
        "equity": 100000.0,
        "cash": 100000.0,
        "buyingPower": 100000.0,
        "peakEquity": 100000.0,
        "currentDrawdownPct": 0.0,
        "dailyStartEquity": 100000.0,
        "dayPnl": 0.0,
        "dayPnlPct": 0.0
      },
      "equityCurve": [
        {
          "t": "2026-06-08T20:37:45.843363+00:00",
          "equity": 100000.0,
          "drawdownPct": 0.0
        },
        {
          "t": "2026-06-08T21:28:49.011875+00:00",
          "equity": 100000.0,
          "drawdownPct": 0.0
        },
        {
          "t": "2026-06-09T21:25:27.745445+00:00",
          "equity": 100000.0,
          "drawdownPct": 0.0
        },
        {
          "t": "2026-06-10T21:47:04.895687+00:00",
          "equity": 100000.0,
          "drawdownPct": 0.0
        },
        {
          "t": "2026-06-11T21:51:28.467608+00:00",
          "equity": 100000.0,
          "drawdownPct": 0.0
        },
        {
          "t": "2026-06-12T21:20:52.826917+00:00",
          "equity": 100000.0,
          "drawdownPct": 0.0
        },
        {
          "t": "2026-06-15T22:06:38.850872+00:00",
          "equity": 100000.0,
          "drawdownPct": 0.0
        },
        {
          "t": "2026-06-16T22:03:27.230156+00:00",
          "equity": 100000.0,
          "drawdownPct": 0.0
        },
        {
          "t": "2026-06-17T21:46:41.907242+00:00",
          "equity": 100000.0,
          "drawdownPct": 0.0
        },
        {
          "t": "2026-06-18T21:52:02.718824+00:00",
          "equity": 100000.0,
          "drawdownPct": 0.0
        },
        {
          "t": "2026-06-19T20:57:12.333036+00:00",
          "equity": 100000.0,
          "drawdownPct": 0.0
        }
      ],
      "positions": [],
      "paperGate": {
        "startDate": "2026-06-08T20:37:45.843363+00:00",
        "daysElapsed": 11,
        "daysRequired": 30,
        "rollingSharpe": 0.0,
        "targetSharpe": 1.0,
        "withinBacktestBand": false
      },
      "summary": {
        "totalReturnPct": 0.0,
        "sharpe": 0.0,
        "maxDrawdownPct": 0.0,
        "dayPnlPct": 0.0,
        "sessions": 11
      }
    },
    {
      "id": "trend_multi_asset",
      "name": "Multi-Asset Trend (5-sleeve)",
      "kind": "experiment",
      "status": "paper",
      "halted": false,
      "account": {
        "equity": 99658.339905,
        "cash": 63383.324905,
        "buyingPower": 63383.324905,
        "peakEquity": 100000.0,
        "currentDrawdownPct": 0.00341660095,
        "dailyStartEquity": 100000.0,
        "dayPnl": -341.660095,
        "dayPnlPct": -0.00341660095
      },
      "equityCurve": [
        {
          "t": "2026-06-08T20:37:44.755588+00:00",
          "equity": 100000.0,
          "drawdownPct": 0.0
        },
        {
          "t": "2026-06-08T21:28:47.929841+00:00",
          "equity": 99954.681725,
          "drawdownPct": 0.00045318274999997814
        },
        {
          "t": "2026-06-09T21:25:26.542632+00:00",
          "equity": 99638.226725,
          "drawdownPct": 0.0036177327499999955
        },
        {
          "t": "2026-06-10T21:47:03.147848+00:00",
          "equity": 98927.221725,
          "drawdownPct": 0.010727782750000043
        },
        {
          "t": "2026-06-11T21:51:26.917934+00:00",
          "equity": 99664.876725,
          "drawdownPct": 0.003351232750000054
        },
        {
          "t": "2026-06-12T21:20:51.531514+00:00",
          "equity": 99681.367625,
          "drawdownPct": 0.0031863237500000105
        },
        {
          "t": "2026-06-15T22:06:37.705971+00:00",
          "equity": 99999.909905,
          "drawdownPct": 9.009500000684057e-07
        },
        {
          "t": "2026-06-16T22:03:25.480199+00:00",
          "equity": 99822.279905,
          "drawdownPct": 0.0017772009499999694
        },
        {
          "t": "2026-06-17T21:46:40.625059+00:00",
          "equity": 99498.314905,
          "drawdownPct": 0.005016850949999934
        },
        {
          "t": "2026-06-18T21:52:01.414238+00:00",
          "equity": 99658.339905,
          "drawdownPct": 0.003416600949999993
        },
        {
          "t": "2026-06-19T20:57:11.179379+00:00",
          "equity": 99658.339905,
          "drawdownPct": 0.003416600949999993
        }
      ],
      "positions": [
        {
          "ticker": "DBC",
          "assetClass": "etf",
          "quantity": 341.0,
          "avgPrice": 29.48946,
          "lastPrice": 27.635,
          "marketValue": 9423.535,
          "unrealizedPnl": -632.37086,
          "unrealizedPnlPct": -0.06288551909733173,
          "weightPct": 0.0945584183820747,
          "strategyId": "multi_asset_trend"
        },
        {
          "ticker": "EFA",
          "assetClass": "etf",
          "quantity": 107.0,
          "avgPrice": 103.0029,
          "lastPrice": 104.39,
          "marketValue": 11169.73,
          "unrealizedPnl": 148.4197,
          "unrealizedPnlPct": 0.013466611134249618,
          "weightPct": 0.11208023343202006,
          "strategyId": "multi_asset_trend"
        },
        {
          "ticker": "SPY",
          "assetClass": "etf",
          "quantity": 21.0,
          "avgPrice": 739.974235,
          "lastPrice": 746.75,
          "marketValue": 15681.75,
          "unrealizedPnl": 142.291065,
          "unrealizedPnlPct": 0.009156758005229736,
          "weightPct": 0.15735511965128796,
          "strategyId": "multi_asset_trend"
        }
      ],
      "paperGate": {
        "startDate": "2026-06-08T20:37:44.755588+00:00",
        "daysElapsed": 11,
        "daysRequired": 30,
        "rollingSharpe": -1.4108886575081239,
        "targetSharpe": 1.0,
        "withinBacktestBand": false
      },
      "summary": {
        "totalReturnPct": -0.0034166009499999594,
        "sharpe": -1.4108886575081239,
        "maxDrawdownPct": 0.010727782750000043,
        "dayPnlPct": -0.00341660095,
        "sessions": 11
      }
    }
  ]
}